nook/__init__.py
nook/commands.py
nook/main.py
nook/utils.py
tests/__init__.py
tests/test_cli.py
tests/test_utils.py
tests/utils.py
venv/bin/activate_this.py
nook-0.1.1.dist-info/METADATA
nook-0.1.1.dist-info/WHEEL
nook-0.1.1.dist-info/entry_points.txt
nook-0.1.1.dist-info/top_level.txt
nook-0.1.1.dist-info/RECORD
