Metadata-Version: 2.1
Name: nook
Version: 0.1.1
Summary: A simple key-value pair management library with CLI
Author-email: Jerry George <jbotrex@gmail.com>
Requires-Python: >=3.6
Requires-Dist: Click
